{"name":"MySQL基础","slug":"MySQL基础","count":1,"postlist":[{"title":"MySQL基础","uid":"4a207b7e885fdbcca8129599135e5f2e","slug":"MySQL基础","date":"2022-09-30T09:27:41.000Z","updated":"2022-09-30T09:28:44.872Z","comments":true,"path":"api/articles/MySQL基础.json","keywords":null,"cover":[],"text":"MySQL 索引结构 - rickiyang - 博客园 (cnblogs.com) MySQL基础1.基础语法 Null 相关 使用 is null，例如查询哪些员工津贴为null： select empno,ename,sal from emp where comm is n...","link":"","photos":[],"count_time":{"symbolsCount":"21k","symbolsTime":"19 mins."},"categories":[],"tags":[{"name":"学习笔记","slug":"学习笔记","count":7,"path":"api/tags/学习笔记.json"},{"name":"MySQL基础","slug":"MySQL基础","count":1,"path":"api/tags/MySQL基础.json"}],"author":{"name":"JuneQQQ","slug":"blog-author","avatar":"https://img-blog.csdnimg.cn/20210313122054101.png","link":"/","description":"一位正在重塑知识的技术人","socials":{"github":"https://github.com/JuneQQQ","twitter":"","stackoverflow":"","wechat":"","qq":"","weibo":"","zhihu":"","csdn":"https://blog.csdn.net/weixin_46925850","juejin":"https://juejin.cn/user/3927934338357197","customs":{}}}}]}